setup.py
kmb_probability/Binomialdistribution.py
kmb_probability/Gaussiandistribution.py
kmb_probability/Generaldistribution.py
kmb_probability/__init__.py
kmb_probability.egg-info/PKG-INFO
kmb_probability.egg-info/SOURCES.txt
kmb_probability.egg-info/dependency_links.txt
kmb_probability.egg-info/not-zip-safe
kmb_probability.egg-info/top_level.txt