Metadata-Version: 1.0
Name: kmb-probability
Version: 0.1
Summary: Binomial and Gaussian distributions
Home-page: UNKNOWN
Author: Mugagga Benjamin
Author-email: mugaggabenjie@gmail.com
License: UNKNOWN
Platform: UNKNOWN
